streamlit_superapp/__init__.py
streamlit_superapp/components.py
streamlit_superapp/index.py
streamlit_superapp/navigation.py
streamlit_superapp/page.py
streamlit_superapp/page_loader.py
streamlit_superapp/performance.py
streamlit_superapp/state.py
streamlit_superapp/typing.py
streamlit_superapp/frontend/.env
streamlit_superapp/frontend/package-lock.json
streamlit_superapp/frontend/package.json
streamlit_superapp/frontend/tsconfig.json
streamlit_superapp/frontend/build/SourceSansPro-Regular.woff2
streamlit_superapp/frontend/build/asset-manifest.json
streamlit_superapp/frontend/build/index.html
streamlit_superapp/frontend/build/static/js/main.e463373a.js
streamlit_superapp/frontend/build/static/js/main.e463373a.js.LICENSE.txt
streamlit_superapp/frontend/build/static/js/main.e463373a.js.map
streamlit_superapp/frontend/public/SourceSansPro-Regular.woff2
streamlit_superapp/frontend/public/index.html
streamlit_superapp/frontend/src/Card.tsx
streamlit_superapp/frontend/src/Grid.tsx
streamlit_superapp/frontend/src/index.tsx
streamlit_superapp/frontend/src/react-app-env.d.ts
streamlit_superapp-1.1.2.dist-info/METADATA
streamlit_superapp-1.1.2.dist-info/WHEEL
streamlit_superapp-1.1.2.dist-info/licenses/LICENSE
streamlit_superapp-1.1.2.dist-info/RECORD
