Metadata-Version: 2.1
Name: streamlit-superapp
Version: 1.1.2
Project-URL: Repository, https://github.com/WilianZilv/streamlit_superapp
Author-email: Wilian <wilianzilv@gmail.com>
License-File: LICENSE
Requires-Python: >=3.8
